{
  "id": "79f1bee7-e6ce-431c-8b3e-72a91cdc34f3",
  "prevId": "4661f6cb-cb88-4800-aad6-e9067093fd34",
  "version": "7",
  "dialect": "postgresql",
  "tables": {
    "public.pools": {
      "name": "pools",
      "schema": "",
      "columns": {
        "id": {
          "name": "id",
          "type": "integer",
          "primaryKey": true,
          "notNull": true,
          "default": 1
        },
        "royalty_pool": {
          "name": "royalty_pool",
          "type": "integer",
          "primaryKey": false,
          "notNull": true,
          "default": 0
        },
        "royalty_reserve": {
          "name": "royalty_reserve",
          "type": "integer",
          "primaryKey": false,
          "notNull": true,
          "default": 0
        },
        "updated_at": {
          "name": "updated_at",
          "type": "timestamp with time zone",
          "primaryKey": false,
          "notNull": true,
          "default": "now()"
        }
      },
      "indexes": {},
      "foreignKeys": {},
      "compositePrimaryKeys": {},
      "uniqueConstraints": {},
      "policies": {},
      "checkConstraints": {},
      "isRLSEnabled": false
    },
    "public.royalty_payouts": {
      "name": "royalty_payouts",
      "schema": "",
      "columns": {
        "id": {
          "name": "id",
          "type": "uuid",
          "primaryKey": true,
          "notNull": true,
          "default": "gen_random_uuid()"
        },
        "run_id": {
          "name": "run_id",
          "type": "uuid",
          "primaryKey": false,
          "notNull": true
        },
        "user_id": {
          "name": "user_id",
          "type": "uuid",
          "primaryKey": false,
          "notNull": true
        },
        "kind": {
          "name": "kind",
          "type": "text",
          "primaryKey": false,
          "notNull": true
        },
        "directs": {
          "name": "directs",
          "type": "integer",
          "primaryKey": false,
          "notNull": false
        },
        "band_percent": {
          "name": "band_percent",
          "type": "integer",
          "primaryKey": false,
          "notNull": false
        },
        "amount": {
          "name": "amount",
          "type": "integer",
          "primaryKey": false,
          "notNull": true
        },
        "created_at": {
          "name": "created_at",
          "type": "timestamp with time zone",
          "primaryKey": false,
          "notNull": true,
          "default": "now()"
        }
      },
      "indexes": {
        "royalty_payouts_run_idx": {
          "name": "royalty_payouts_run_idx",
          "columns": [
            {
              "expression": "run_id",
              "isExpression": false,
              "asc": true,
              "nulls": "last"
            }
          ],
          "isUnique": false,
          "concurrently": false,
          "method": "btree",
          "with": {}
        },
        "royalty_payouts_user_idx": {
          "name": "royalty_payouts_user_idx",
          "columns": [
            {
              "expression": "user_id",
              "isExpression": false,
              "asc": true,
              "nulls": "last"
            }
          ],
          "isUnique": false,
          "concurrently": false,
          "method": "btree",
          "with": {}
        }
      },
      "foreignKeys": {},
      "compositePrimaryKeys": {},
      "uniqueConstraints": {},
      "policies": {},
      "checkConstraints": {},
      "isRLSEnabled": false
    },
    "public.royalty_runs": {
      "name": "royalty_runs",
      "schema": "",
      "columns": {
        "id": {
          "name": "id",
          "type": "uuid",
          "primaryKey": true,
          "notNull": true,
          "default": "gen_random_uuid()"
        },
        "pool_before": {
          "name": "pool_before",
          "type": "integer",
          "primaryKey": false,
          "notNull": true
        },
        "reserve_added": {
          "name": "reserve_added",
          "type": "integer",
          "primaryKey": false,
          "notNull": true
        },
        "rank_distributed": {
          "name": "rank_distributed",
          "type": "integer",
          "primaryKey": false,
          "notNull": true
        },
        "reserve_distributed": {
          "name": "reserve_distributed",
          "type": "integer",
          "primaryKey": false,
          "notNull": true
        },
        "rank_recipients": {
          "name": "rank_recipients",
          "type": "integer",
          "primaryKey": false,
          "notNull": true
        },
        "reserve_recipients": {
          "name": "reserve_recipients",
          "type": "integer",
          "primaryKey": false,
          "notNull": true
        },
        "created_at": {
          "name": "created_at",
          "type": "timestamp with time zone",
          "primaryKey": false,
          "notNull": true,
          "default": "now()"
        }
      },
      "indexes": {},
      "foreignKeys": {},
      "compositePrimaryKeys": {},
      "uniqueConstraints": {},
      "policies": {},
      "checkConstraints": {},
      "isRLSEnabled": false
    },
    "public.royalty_tiers": {
      "name": "royalty_tiers",
      "schema": "",
      "columns": {
        "min_directs": {
          "name": "min_directs",
          "type": "integer",
          "primaryKey": true,
          "notNull": true
        },
        "percent": {
          "name": "percent",
          "type": "integer",
          "primaryKey": false,
          "notNull": true
        },
        "label": {
          "name": "label",
          "type": "text",
          "primaryKey": false,
          "notNull": true
        }
      },
      "indexes": {},
      "foreignKeys": {},
      "compositePrimaryKeys": {},
      "uniqueConstraints": {},
      "policies": {},
      "checkConstraints": {},
      "isRLSEnabled": false
    },
    "public.settings": {
      "name": "settings",
      "schema": "",
      "columns": {
        "id": {
          "name": "id",
          "type": "integer",
          "primaryKey": true,
          "notNull": true,
          "default": 1
        },
        "join_fee": {
          "name": "join_fee",
          "type": "integer",
          "primaryKey": false,
          "notNull": true,
          "default": 10
        },
        "id_pin_fee": {
          "name": "id_pin_fee",
          "type": "integer",
          "primaryKey": false,
          "notNull": true,
          "default": 10
        },
        "sponsor_reward": {
          "name": "sponsor_reward",
          "type": "integer",
          "primaryKey": false,
          "notNull": true,
          "default": 5
        },
        "royalty_fee": {
          "name": "royalty_fee",
          "type": "integer",
          "primaryKey": false,
          "notNull": true,
          "default": 10
        },
        "royalty_reserve_percent": {
          "name": "royalty_reserve_percent",
          "type": "integer",
          "primaryKey": false,
          "notNull": true,
          "default": 5
        },
        "reserve_inactivity_months": {
          "name": "reserve_inactivity_months",
          "type": "integer",
          "primaryKey": false,
          "notNull": true,
          "default": 6
        },
        "company_percent": {
          "name": "company_percent",
          "type": "integer",
          "primaryKey": false,
          "notNull": true,
          "default": 0
        },
        "auto_place": {
          "name": "auto_place",
          "type": "boolean",
          "primaryKey": false,
          "notNull": true,
          "default": true
        },
        "updated_at": {
          "name": "updated_at",
          "type": "timestamp with time zone",
          "primaryKey": false,
          "notNull": true,
          "default": "now()"
        }
      },
      "indexes": {},
      "foreignKeys": {},
      "compositePrimaryKeys": {},
      "uniqueConstraints": {},
      "policies": {},
      "checkConstraints": {},
      "isRLSEnabled": false
    },
    "public.slab_completions": {
      "name": "slab_completions",
      "schema": "",
      "columns": {
        "id": {
          "name": "id",
          "type": "uuid",
          "primaryKey": true,
          "notNull": true,
          "default": "gen_random_uuid()"
        },
        "user_id": {
          "name": "user_id",
          "type": "uuid",
          "primaryKey": false,
          "notNull": true
        },
        "slab_level": {
          "name": "slab_level",
          "type": "integer",
          "primaryKey": false,
          "notNull": true
        },
        "collected": {
          "name": "collected",
          "type": "integer",
          "primaryKey": false,
          "notNull": true
        },
        "status": {
          "name": "status",
          "type": "choice_status",
          "typeSchema": "public",
          "primaryKey": false,
          "notNull": true,
          "default": "'pending'"
        },
        "payout": {
          "name": "payout",
          "type": "integer",
          "primaryKey": false,
          "notNull": false
        },
        "created_at": {
          "name": "created_at",
          "type": "timestamp with time zone",
          "primaryKey": false,
          "notNull": true,
          "default": "now()"
        },
        "decided_at": {
          "name": "decided_at",
          "type": "timestamp with time zone",
          "primaryKey": false,
          "notNull": false
        }
      },
      "indexes": {
        "completions_user_idx": {
          "name": "completions_user_idx",
          "columns": [
            {
              "expression": "user_id",
              "isExpression": false,
              "asc": true,
              "nulls": "last"
            }
          ],
          "isUnique": false,
          "concurrently": false,
          "method": "btree",
          "with": {}
        },
        "completions_uniq_idx": {
          "name": "completions_uniq_idx",
          "columns": [
            {
              "expression": "user_id",
              "isExpression": false,
              "asc": true,
              "nulls": "last"
            },
            {
              "expression": "slab_level",
              "isExpression": false,
              "asc": true,
              "nulls": "last"
            }
          ],
          "isUnique": true,
          "concurrently": false,
          "method": "btree",
          "with": {}
        }
      },
      "foreignKeys": {},
      "compositePrimaryKeys": {},
      "uniqueConstraints": {},
      "policies": {},
      "checkConstraints": {},
      "isRLSEnabled": false
    },
    "public.slabs": {
      "name": "slabs",
      "schema": "",
      "columns": {
        "level": {
          "name": "level",
          "type": "integer",
          "primaryKey": true,
          "notNull": true
        },
        "name": {
          "name": "name",
          "type": "text",
          "primaryKey": false,
          "notNull": true
        },
        "fee": {
          "name": "fee",
          "type": "integer",
          "primaryKey": false,
          "notNull": true
        },
        "slots": {
          "name": "slots",
          "type": "integer",
          "primaryKey": false,
          "notNull": true
        },
        "referral_bonus": {
          "name": "referral_bonus",
          "type": "integer",
          "primaryKey": false,
          "notNull": true,
          "default": 0
        },
        "exit_percent": {
          "name": "exit_percent",
          "type": "integer",
          "primaryKey": false,
          "notNull": true,
          "default": 30
        },
        "upgrade_take_percent": {
          "name": "upgrade_take_percent",
          "type": "integer",
          "primaryKey": false,
          "notNull": true,
          "default": 25
        },
        "active": {
          "name": "active",
          "type": "boolean",
          "primaryKey": false,
          "notNull": true,
          "default": true
        },
        "sort_order": {
          "name": "sort_order",
          "type": "integer",
          "primaryKey": false,
          "notNull": true,
          "default": 0
        }
      },
      "indexes": {},
      "foreignKeys": {},
      "compositePrimaryKeys": {},
      "uniqueConstraints": {},
      "policies": {},
      "checkConstraints": {},
      "isRLSEnabled": false
    },
    "public.slots": {
      "name": "slots",
      "schema": "",
      "columns": {
        "id": {
          "name": "id",
          "type": "uuid",
          "primaryKey": true,
          "notNull": true,
          "default": "gen_random_uuid()"
        },
        "owner_id": {
          "name": "owner_id",
          "type": "uuid",
          "primaryKey": false,
          "notNull": true
        },
        "slab_level": {
          "name": "slab_level",
          "type": "integer",
          "primaryKey": false,
          "notNull": true
        },
        "position": {
          "name": "position",
          "type": "integer",
          "primaryKey": false,
          "notNull": true
        },
        "status": {
          "name": "status",
          "type": "slot_status",
          "typeSchema": "public",
          "primaryKey": false,
          "notNull": true,
          "default": "'open'"
        },
        "occupant_id": {
          "name": "occupant_id",
          "type": "uuid",
          "primaryKey": false,
          "notNull": false
        },
        "queue_seq": {
          "name": "queue_seq",
          "type": "serial",
          "primaryKey": false,
          "notNull": true
        },
        "created_at": {
          "name": "created_at",
          "type": "timestamp with time zone",
          "primaryKey": false,
          "notNull": true,
          "default": "now()"
        },
        "filled_at": {
          "name": "filled_at",
          "type": "timestamp with time zone",
          "primaryKey": false,
          "notNull": false
        }
      },
      "indexes": {
        "slots_fifo_idx": {
          "name": "slots_fifo_idx",
          "columns": [
            {
              "expression": "slab_level",
              "isExpression": false,
              "asc": true,
              "nulls": "last"
            },
            {
              "expression": "status",
              "isExpression": false,
              "asc": true,
              "nulls": "last"
            },
            {
              "expression": "queue_seq",
              "isExpression": false,
              "asc": true,
              "nulls": "last"
            }
          ],
          "isUnique": false,
          "concurrently": false,
          "method": "btree",
          "with": {}
        },
        "slots_owner_idx": {
          "name": "slots_owner_idx",
          "columns": [
            {
              "expression": "owner_id",
              "isExpression": false,
              "asc": true,
              "nulls": "last"
            },
            {
              "expression": "slab_level",
              "isExpression": false,
              "asc": true,
              "nulls": "last"
            }
          ],
          "isUnique": false,
          "concurrently": false,
          "method": "btree",
          "with": {}
        }
      },
      "foreignKeys": {},
      "compositePrimaryKeys": {},
      "uniqueConstraints": {},
      "policies": {},
      "checkConstraints": {},
      "isRLSEnabled": false
    },
    "public.transactions": {
      "name": "transactions",
      "schema": "",
      "columns": {
        "id": {
          "name": "id",
          "type": "uuid",
          "primaryKey": true,
          "notNull": true,
          "default": "gen_random_uuid()"
        },
        "user_id": {
          "name": "user_id",
          "type": "uuid",
          "primaryKey": false,
          "notNull": true
        },
        "type": {
          "name": "type",
          "type": "tx_type",
          "typeSchema": "public",
          "primaryKey": false,
          "notNull": true
        },
        "points": {
          "name": "points",
          "type": "integer",
          "primaryKey": false,
          "notNull": true
        },
        "balance_after": {
          "name": "balance_after",
          "type": "integer",
          "primaryKey": false,
          "notNull": true
        },
        "counterparty_id": {
          "name": "counterparty_id",
          "type": "uuid",
          "primaryKey": false,
          "notNull": false
        },
        "slab_level": {
          "name": "slab_level",
          "type": "integer",
          "primaryKey": false,
          "notNull": false
        },
        "note": {
          "name": "note",
          "type": "text",
          "primaryKey": false,
          "notNull": false
        },
        "meta": {
          "name": "meta",
          "type": "jsonb",
          "primaryKey": false,
          "notNull": false
        },
        "idempotency_key": {
          "name": "idempotency_key",
          "type": "text",
          "primaryKey": false,
          "notNull": false
        },
        "created_at": {
          "name": "created_at",
          "type": "timestamp with time zone",
          "primaryKey": false,
          "notNull": true,
          "default": "now()"
        }
      },
      "indexes": {
        "tx_user_idx": {
          "name": "tx_user_idx",
          "columns": [
            {
              "expression": "user_id",
              "isExpression": false,
              "asc": true,
              "nulls": "last"
            },
            {
              "expression": "created_at",
              "isExpression": false,
              "asc": true,
              "nulls": "last"
            }
          ],
          "isUnique": false,
          "concurrently": false,
          "method": "btree",
          "with": {}
        },
        "tx_user_slab_idx": {
          "name": "tx_user_slab_idx",
          "columns": [
            {
              "expression": "user_id",
              "isExpression": false,
              "asc": true,
              "nulls": "last"
            },
            {
              "expression": "slab_level",
              "isExpression": false,
              "asc": true,
              "nulls": "last"
            }
          ],
          "isUnique": false,
          "concurrently": false,
          "method": "btree",
          "with": {}
        },
        "tx_idem_idx": {
          "name": "tx_idem_idx",
          "columns": [
            {
              "expression": "idempotency_key",
              "isExpression": false,
              "asc": true,
              "nulls": "last"
            }
          ],
          "isUnique": true,
          "concurrently": false,
          "method": "btree",
          "with": {}
        }
      },
      "foreignKeys": {},
      "compositePrimaryKeys": {},
      "uniqueConstraints": {},
      "policies": {},
      "checkConstraints": {},
      "isRLSEnabled": false
    },
    "public.users": {
      "name": "users",
      "schema": "",
      "columns": {
        "id": {
          "name": "id",
          "type": "uuid",
          "primaryKey": true,
          "notNull": true,
          "default": "gen_random_uuid()"
        },
        "email": {
          "name": "email",
          "type": "text",
          "primaryKey": false,
          "notNull": true
        },
        "password_hash": {
          "name": "password_hash",
          "type": "text",
          "primaryKey": false,
          "notNull": true
        },
        "name": {
          "name": "name",
          "type": "text",
          "primaryKey": false,
          "notNull": true
        },
        "role": {
          "name": "role",
          "type": "user_role",
          "typeSchema": "public",
          "primaryKey": false,
          "notNull": true,
          "default": "'user'"
        },
        "status": {
          "name": "status",
          "type": "user_status",
          "typeSchema": "public",
          "primaryKey": false,
          "notNull": true,
          "default": "'registered'"
        },
        "sponsor_id": {
          "name": "sponsor_id",
          "type": "uuid",
          "primaryKey": false,
          "notNull": false
        },
        "referral_code": {
          "name": "referral_code",
          "type": "text",
          "primaryKey": false,
          "notNull": true
        },
        "current_slab": {
          "name": "current_slab",
          "type": "integer",
          "primaryKey": false,
          "notNull": true,
          "default": 0
        },
        "pending_choice_slab": {
          "name": "pending_choice_slab",
          "type": "integer",
          "primaryKey": false,
          "notNull": false
        },
        "points_balance": {
          "name": "points_balance",
          "type": "integer",
          "primaryKey": false,
          "notNull": true,
          "default": 0
        },
        "created_at": {
          "name": "created_at",
          "type": "timestamp with time zone",
          "primaryKey": false,
          "notNull": true,
          "default": "now()"
        },
        "activated_at": {
          "name": "activated_at",
          "type": "timestamp with time zone",
          "primaryKey": false,
          "notNull": false
        },
        "exited_at": {
          "name": "exited_at",
          "type": "timestamp with time zone",
          "primaryKey": false,
          "notNull": false
        },
        "last_stage_cleared_at": {
          "name": "last_stage_cleared_at",
          "type": "timestamp with time zone",
          "primaryKey": false,
          "notNull": false
        },
        "last_reserve_reward_at": {
          "name": "last_reserve_reward_at",
          "type": "timestamp with time zone",
          "primaryKey": false,
          "notNull": false
        }
      },
      "indexes": {
        "users_email_idx": {
          "name": "users_email_idx",
          "columns": [
            {
              "expression": "email",
              "isExpression": false,
              "asc": true,
              "nulls": "last"
            }
          ],
          "isUnique": true,
          "concurrently": false,
          "method": "btree",
          "with": {}
        },
        "users_referral_code_idx": {
          "name": "users_referral_code_idx",
          "columns": [
            {
              "expression": "referral_code",
              "isExpression": false,
              "asc": true,
              "nulls": "last"
            }
          ],
          "isUnique": true,
          "concurrently": false,
          "method": "btree",
          "with": {}
        },
        "users_sponsor_idx": {
          "name": "users_sponsor_idx",
          "columns": [
            {
              "expression": "sponsor_id",
              "isExpression": false,
              "asc": true,
              "nulls": "last"
            }
          ],
          "isUnique": false,
          "concurrently": false,
          "method": "btree",
          "with": {}
        }
      },
      "foreignKeys": {},
      "compositePrimaryKeys": {},
      "uniqueConstraints": {},
      "policies": {},
      "checkConstraints": {},
      "isRLSEnabled": false
    }
  },
  "enums": {
    "public.choice_status": {
      "name": "choice_status",
      "schema": "public",
      "values": [
        "pending",
        "exited",
        "upgraded"
      ]
    },
    "public.slot_status": {
      "name": "slot_status",
      "schema": "public",
      "values": [
        "open",
        "filled"
      ]
    },
    "public.tx_type": {
      "name": "tx_type",
      "schema": "public",
      "values": [
        "join_fee",
        "id_pin_fee",
        "royalty_fee",
        "activation_fee",
        "upgrade_fee",
        "slot_credit",
        "referral_bonus",
        "exit_payout",
        "upgrade_take",
        "company_fee",
        "royalty_payout",
        "royalty_reserve_reward",
        "adjustment"
      ]
    },
    "public.user_role": {
      "name": "user_role",
      "schema": "public",
      "values": [
        "user",
        "admin"
      ]
    },
    "public.user_status": {
      "name": "user_status",
      "schema": "public",
      "values": [
        "registered",
        "active",
        "exited",
        "completed"
      ]
    }
  },
  "schemas": {},
  "sequences": {},
  "roles": {},
  "policies": {},
  "views": {},
  "_meta": {
    "columns": {},
    "schemas": {},
    "tables": {}
  }
}